pass_master/__init__.py
pass_master/cli.py
pass_master/password_store.py
pass_master-1.0.1.dist-info/entry_points.txt
pass_master-1.0.1.dist-info/LICENSE
pass_master-1.0.1.dist-info/METADATA
pass_master-1.0.1.dist-info/WHEEL
pass_master-1.0.1.dist-info/RECORD
