Metadata-Version: 2.1
Name: pass-master
Version: 1.0.1
Summary: Password manager from the terminal!
Home-page: https://github.com/Maxthecoder123/pass-master
License: MIT
Keywords: password,manager,cli,security,encryption
Author: Your Name
Author-email: you@example.com
Requires-Python: >=3.12,<4.0
Classifier: Development Status :: 4 - Beta
Classifier: Environment :: Console
Classifier: Intended Audience :: End Users/Desktop
Classifier: License :: OSI Approved :: MIT License
Classifier: Programming Language :: Python :: 3
Classifier: Programming Language :: Python :: 3.12
Classifier: Programming Language :: Python :: 3.13
Classifier: Topic :: Security
Classifier: Topic :: Utilities
Requires-Dist: click (>=8.1.8,<9.0.0)
Requires-Dist: colorama (>=0.4.6,<0.5.0)
Requires-Dist: cryptography (>=42.0.5,<43.0.0)
Requires-Dist: keyring (>=24.3.1,<25.0.0)
Requires-Dist: password-strength (>=0.0.3.post2,<0.0.4)
Requires-Dist: pyperclip (>=1.8.2,<2.0.0)
Requires-Dist: rich (>=13.7.0,<14.0.0)
Project-URL: Repository, https://github.com/Maxthecoder123/pass-master
